ni_measurement_plugin_sdk_generator/__init__.py
ni_measurement_plugin_sdk_generator/client/__init__.py
ni_measurement_plugin_sdk_generator/client/__main__.py
ni_measurement_plugin_sdk_generator/client/_support.py
ni_measurement_plugin_sdk_generator/client/templates/measurement_plugin_client.py.mako
ni_measurement_plugin_sdk_generator/plugin/__init__.py
ni_measurement_plugin_sdk_generator/plugin/__main__.py
ni_measurement_plugin_sdk_generator/plugin/templates/_helpers.py.mako
ni_measurement_plugin_sdk_generator/plugin/templates/measurement.measproj.mako
ni_measurement_plugin_sdk_generator/plugin/templates/measurement.measui.mako
ni_measurement_plugin_sdk_generator/plugin/templates/measurement.py.mako
ni_measurement_plugin_sdk_generator/plugin/templates/measurement.serviceconfig.mako
ni_measurement_plugin_sdk_generator/plugin/templates/start.bat.mako
ni_measurement_plugin_sdk_generator/py.typed
ni_measurement_plugin_sdk_generator-3.1.0.dist-info/METADATA
ni_measurement_plugin_sdk_generator-3.1.0.dist-info/WHEEL
ni_measurement_plugin_sdk_generator-3.1.0.dist-info/entry_points.txt
ni_measurement_plugin_sdk_generator-3.1.0.dist-info/RECORD
