Metadata-Version: 2.3
Name: ni_measurement_plugin_sdk_generator
Version: 3.1.0
Summary: Measurement Plug-In Code Generator for Python
License: MIT
Author: NI
Author-email: opensource@ni.com
Requires-Python: >=3.10,<4.0
Classifier: Development Status :: 5 - Production/Stable
Classifier: Intended Audience :: Developers
Classifier: Intended Audience :: Manufacturing
Classifier: Intended Audience :: Science/Research
Classifier: License :: OSI Approved :: MIT License
Classifier: Operating System :: Microsoft :: Windows
Classifier: Programming Language :: Python :: 3
Classifier: Programming Language :: Python :: 3.10
Classifier: Programming Language :: Python :: 3.11
Classifier: Programming Language :: Python :: 3.12
Classifier: Programming Language :: Python :: 3.13
Classifier: Programming Language :: Python :: Implementation :: CPython
Classifier: Topic :: Scientific/Engineering
Classifier: Topic :: System :: Hardware
Requires-Dist: Mako (>=1.2.1,<2.0.0)
Requires-Dist: black (>=24.8.0)
Requires-Dist: click (>=8.1.3)
Requires-Dist: click-option-group (>=0.5.6)
Requires-Dist: grpcio (>=1.49.1,<2.0.0)
Requires-Dist: ni-grpc-extensions (>=1.0.0,<2.0.0)
Requires-Dist: ni-grpcdevice-v1-proto (>=1.0.0,<2.0.0)
Requires-Dist: ni-measurement-plugin-sdk-service (>=2.2.0)
Requires-Dist: ni-measurementlink-discovery-v1-client (>=1.0.0,<2.0.0)
Requires-Dist: ni-measurementlink-pinmap-v1-client (>=1.0.0,<2.0.0)
Requires-Dist: ni-protobuf-types (>=1.0.0,<2.0.0)
Requires-Dist: protobuf (>=4.21)
Project-URL: Repository, https://github.com/ni/measurement-plugin-python/
